LICENSE
README.md
setup.py
adda_for_floodwater/__init__.py
adda_for_floodwater/adda.py
adda_for_floodwater/adda_visualization_plots.py
adda_for_floodwater.egg-info/PKG-INFO
adda_for_floodwater.egg-info/SOURCES.txt
adda_for_floodwater.egg-info/dependency_links.txt
adda_for_floodwater.egg-info/requires.txt
adda_for_floodwater.egg-info/top_level.txt